wxauto4/__init__.py
wxauto4/__main__.py
wxauto4/exceptions.py
wxauto4/languages.py
wxauto4/logger.py
wxauto4/msgs/__init__.py
wxauto4/msgs/base.py
wxauto4/msgs/friend.py
wxauto4/msgs/mattr.py
wxauto4/msgs/msg.py
wxauto4/msgs/mtype.py
wxauto4/msgs/parse.py
wxauto4/msgs/self.py
wxauto4/param.py
wxauto4/ui/__init__.py
wxauto4/ui/base.py
wxauto4/ui/chatbox.py
wxauto4/ui/component.py
wxauto4/ui/main.py
wxauto4/ui/navigationbox.py
wxauto4/ui/sessionbox.py
wxauto4/uia/__init__.py
wxauto4/uia/uiautomation.py
wxauto4/utils/__init__.py
wxauto4/utils/lock.py
wxauto4/utils/tools.py
wxauto4/utils/win32.py
wxauto4/wx.py
wxauto4-40.1.3.dist-info/entry_points.txt
wxauto4-40.1.3.dist-info/METADATA
wxauto4-40.1.3.dist-info/WHEEL
wxauto4-40.1.3.dist-info/RECORD
