Metadata-Version: 2.4
Name: wxauto4
Version: 40.1.3
Summary: wxauto for 4.0 client
Author: Cluic
Author-email: tikic@qq.com
Requires-Python: >=3.9,<3.14
Classifier: Programming Language :: Python :: 3
Classifier: Programming Language :: Python :: 3.9
Classifier: Programming Language :: Python :: 3.10
Classifier: Programming Language :: Python :: 3.11
Classifier: Programming Language :: Python :: 3.12
Classifier: Programming Language :: Python :: 3.13
Requires-Dist: colorama
Requires-Dist: comtypes
Requires-Dist: pillow
Requires-Dist: psutil
Requires-Dist: pyperclip
Requires-Dist: pywin32
Requires-Dist: tenacity
